nb_execute/__init__.py
nb_execute/execution.py
nb_execute-1.0.0.dist-info/METADATA
nb_execute-1.0.0.dist-info/WHEEL
nb_execute-1.0.0.dist-info/top_level.txt
nb_execute-1.0.0.dist-info/RECORD
